telegramcloud/__main__.py
telegramcloud/add_session.py
telegramcloud/telegram_config.py
telegramcloud/scripts/tginfo.py
telegramcloud/scripts/tgsend.py
telegramcloud/scripts/tgutil.py
telegramcloud/utils/args.py
telegramcloud/utils/utils.py
telegram_cloud-1.4.4.dist-info/LICENSE
telegram_cloud-1.4.4.dist-info/METADATA
telegram_cloud-1.4.4.dist-info/WHEEL
telegram_cloud-1.4.4.dist-info/entry_points.txt
telegram_cloud-1.4.4.dist-info/top_level.txt
telegram_cloud-1.4.4.dist-info/RECORD
