Metadata-Version: 2.1
Name: telegram-cloud
Version: 1.4.4
Summary: Download and upload files via telegram up to 2 GB, CLI
Home-page: https://github.com/iw4p/telegram-cloud
Author: Nima Akbarzade
Author-email: Nimakbarzade@yahoo.com
License: MIT
Platform: UNKNOWN
Classifier: License :: OSI Approved :: MIT License
Classifier: Programming Language :: Python :: 3
Classifier: Programming Language :: Python :: 3.7
Requires-Dist: telethon
Requires-Dist: cryptg
